Workbook

Sheet Summary
B2: TCS — 3-Statement Model & DCF Valuation
B3: Quick-read summary. See Assumptions, 3-Statement Model, DCF Valuation, and Sensitivity Analysis tabs for full detail.
B6: INTRINSIC VALUE / SHARE | D6: CURRENT MARKET PRICE | F6: IMPLIED UPSIDE | H6: WACC USED
B7: ='DCF Valuation'!D24 -> 2438.5007 | D7: ='DCF Valuation'!D27 -> 2268 | F7: ='DCF Valuation'!D28 -> 0.075176685 | H7: =Assumptions!D24 -> 0.11785314
B9: Verdict: | C9: ='DCF Valuation'!D29 -> FAIRLY VALUED
B12: Revenue: Historical Actuals (FY21–FY26) & Projected (FY27E–FY31E)

Sheet Assumptions
B2: TCS — 3-Statement Model & DCF Valuation
B3: Assumptions & Inputs | Blue cells = inputs (editable) | Black cells = formulas
B5: Cost of Equity (CAPM)
B6: Risk-Free Rate (India 10Y G-Sec) | D6: 0.068
B7: Beta (5Y, vs Nifty 50) | D7: 0.78
B8: Equity Risk Premium (India) | D8: 0.065
B9: Cost of Equity (Ke) = Rf + β × ERP | D9: =D6+D7*D8 -> 0.1187
B11: Cost of Debt
B12: Pre-Tax Cost of Debt | D12: 0.075
B13: Effective Tax Rate | D13: 0.25
B14: Post-Tax Cost of Debt | D14: =D12*(1-D13) -> 0.05625
B16: Capital Structure (Market-Value Weights)
B17: Market Capitalisation (₹ Cr) | D17: 820763
B18: Total Borrowings / Lease Liabilities (₹ Cr) | D18: 11283
B19: Total Capital Employed (₹ Cr) | D19: =D17+D18 -> 832046
B20: Weight of Equity | D20: =D17/D19 -> 0.98643945
B21: Weight of Debt | D21: =D18/D19 -> 0.013560548
B23: Weighted Average Cost of Capital
B24: WACC = We×Ke + Wd×Kd(1-t) | D24: =D20*D9+D21*D14 -> 0.11785314
B26: Terminal Value Assumption
B27: Terminal (Perpetuity) Growth Rate | D27: 0.05
B29: Net Cash / Share Data (FY26 Actuals)
B30: Cash & Investments (₹ Cr) | D30: 48714
B31: Borrowings / Lease Liabilities (₹ Cr) | D31: =D18 -> 11283
B32: Net Cash / (Net Debt) (₹ Cr) | D32: =D30-D31 -> 37431
B33: Shares Outstanding (Cr) | D33: 361.89
B34: Current Share Price (₹, as of Aug 2026) | D34: 2268
B36: Revenue Growth Assumptions (Projection Years)
D37: FY27E | E37: FY28E | F37: FY29E | G37: FY30E | H37: FY31E
B38: YoY Revenue Growth % | D38: 0.09 | E38: 0.085 | F38: 0.08 | G38: 0.075 | H38: 0.07
B40: Margin Assumptions (Held Constant Through Projection)
B41: Operating Margin (OPM) | D41: 0.27
B42: Free Cash Flow Margin (FCF / Revenue) | D42: 0.18
B43: D&A (% of Revenue) | D43: 0.0208
B45: Sources: screener.in (consolidated financials, FY26); India 10Y G-Sec via tradingeconomics.com (Aug 2026); Beta and ERP are illustrative estimates for a large-cap Indian IT services company.

Sheet 3-Statement Model
B2: TCS — Income Statement, Balance Sheet & Cash Flow
B3: Consolidated, ₹ Crores | FY21–FY26 Actuals (screener.in) | FY27E–FY31E Projected (formula-driven, shaded)
B5: (₹ Crores) | C5: FY21 | D5: FY22 | E5: FY23 | F5: FY24 | G5: FY25 | H5: FY26 | I5: FY27E | J5: FY28E | K5: FY29E | L5: FY30E | M5: FY31E
B7: INCOME STATEMENT
B8: Revenue | C8: 164177 | D8: 191754 | E8: 225458 | F8: 240893 | G8: 255324 | H8: 267021 | I8: =H8*(1+Assumptions!D38) -> 291052.89 | J8: =I8*(1+Assumptions!E38) -> 315792.39 | K8: =J8*(1+Assumptions!F38) -> 341055.78 | L8: =K8*(1+Assumptions!G38) -> 366634.96 | M8: =L8*(1+Assumptions!H38) -> 392299.41
B9: Revenue Growth % YoY | D9: =(D8-C8)/C8 -> 0.16797115 | E9: =(E8-D8)/D8 -> 0.17576687 | F9: =(F8-E8)/E8 -> 0.068460645 | G9: =(G8-F8)/F8 -> 0.059906265 | H9: =(H8-G8)/G8 -> 0.04581238 | I9: =(I8-H8)/H8 -> 0.09 | J9: =(J8-I8)/I8 -> 0.085 | K9: =(K8-J8)/J8 -> 0.08 | ... M9: =(M8-L8)/L8 -> 0.07
B10: Operating Profit (EBIT) | C10: 46546 | D10: 53057 | E10: 59259 | F10: 64296 | G10: 67407 | H10: 72398 | I10: =I8*Assumptions!$D$41 -> 78584.28 | J10: =J8*Assumptions!$D$41 -> 85263.944 | K10: =K8*Assumptions!$D$41 -> 92085.06 | L10: =L8*Assumptions!$D$41 -> 98991.439 | M10: =M8*Assumptions!$D$41 -> 105920.84
B11: Operating Margin (OPM %) | C11: =C10/C8 -> 0.28351109 | D11: =D10/D8 -> 0.27669305 | E11: =E10/E8 -> 0.26283831 | F11: =F10/F8 -> 0.26690688 | G11: =G10/G8 -> 0.26400573 | H11: =H10/H8 -> 0.27113223 | I11: =I10/I8 -> 0.27 | J11: =J10/J8 -> 0.27 | ... M11: =M10/M8 -> 0.27
B12: Other Income | C12: 1916 | D12: 4018 | E12: 3449 | F12: 3464 | G12: 3962 | H12: -124 | I12: 0 | J12: 0 | K12: 0 | L12: 0 | M12: 0
B13: Interest Expense | C13: 637 | D13: 784 | E13: 779 | F13: 778 | G13: 796 | H13: 1227 | I13: =$F$13 -> 778 | J13: =$F$13 -> 778 | K13: =$F$13 -> 778 | L13: =$F$13 -> 778 | M13: =$F$13 -> 778
B14: Depreciation & Amortisation | C14: 4065 | D14: 4604 | E14: 5022 | F14: 4985 | G14: 5242 | H14: 5560 | I14: =I8*Assumptions!$D$43 -> 6053.9001 | J14: =J8*Assumptions!$D$43 -> 6568.4816 | K14: =K8*Assumptions!$D$43 -> 7093.9602 | L14: =L8*Assumptions!$D$43 -> 7626.0072 | M14: =M8*Assumptions!$D$43 -> 8159.8277
B15: Profit Before Tax | C15: 43760 | D15: 51687 | E15: 56907 | F15: 61997 | G15: 65331 | H15: 65487 | I15: =I10+I12-I13-I14 -> 71752.38 | J15: =J10+J12-J13-J14 -> 77917.463 | K15: =K10+K12-K13-K14 -> 84213.1 | L15: =L10+L12-L13-L14 -> 90587.432 | M15: =M10+M12-M13-M14 -> 96983.012
B16: Tax Rate % | C16: 0.26 | D16: 0.26 | E16: 0.26 | F16: 0.26 | G16: 0.25 | H16: 0.24 | I16: =Assumptions!$D$13 -> 0.25 | J16: =Assumptions!$D$13 -> 0.25 | K16: =Assumptions!$D$13 -> 0.25 | L16: =Assumptions!$D$13 -> 0.25 | M16: =Assumptions!$D$13 -> 0.25
B17: Net Profit | C17: 32562 | D17: 38449 | E17: 42303 | F17: 46099 | G17: 48797 | H17: 49454 | I17: =I15*(1-I16) -> 53814.285 | J17: =J15*(1-J16) -> 58438.097 | K17: =K15*(1-K16) -> 63159.825 | L17: =L15*(1-L16) -> 67940.574 | M17: =M15*(1-M16) -> 72737.259
B18: EPS (₹) | C18: 87.67 | D18: 104.75 | E18: 115.19 | F18: 126.88 | G18: 134.2 | H18: 136.01 | I18: =I17/Assumptions!$D$33 -> 148.70343 | J18: =J17/Assumptions!$D$33 -> 161.48028 | K18: =K17/Assumptions!$D$33 -> 174.52769 | L18: =L17/Assumptions!$D$33 -> 187.73819 | M18: =M17/Assumptions!$D$33 -> 200.99273
B20: BALANCE SHEET (Historical Actuals)
B21: Equity Capital | C21: 370 | D21: 366 | E21: 366 | F21: 362 | G21: 362 | H21: 362
B22: Reserves & Surplus | C22: 86063 | D22: 88773 | E22: 90058 | F22: 90127 | G22: 94394 | H22: 106878
B23: Total Equity | C23: =C21+C22 -> 86433 | D23: =D21+D22 -> 89139 | E23: =E21+E22 -> 90424 | F23: =F21+F22 -> 90489 | G23: =G21+G22 -> 94756 | H23: =H21+H22 -> 107240
B24: Borrowings / Lease Liabilities | C24: 7795 | D24: 7818 | E24: 7688 | F24: 8021 | G24: 9392 | H24: 11283
B25: Other Liabilities | C25: 35764 | D25: 43967 | E25: 44747 | F25: 46962 | G25: 54501 | H25: 62644
B26: Total Liabilities & Equity | C26: =C23+C24+C25 -> 129992 | D26: =D23+D24+D25 -> 140924 | E26: =E23+E24+E25 -> 142859 | F26: =F23+F24+F25 -> 145472 | G26: =G23+G24+G25 -> 158649 | H26: =H23+H24+H25 -> 181167
B28: CASH FLOW
B29: Cash from Operating Activity | C29: 38802 | D29: 39949 | E29: 41965 | F29: 44338 | G29: 48908 | H29: 52094
B30: Free Cash Flow (FCF) | C30: 35663 | D30: 36985 | E30: 38902 | F30: 41688 | G30: 44994 | H30: 48013 | I30: =I8*Assumptions!$D$42 -> 52389.52 | J30: =J8*Assumptions!$D$42 -> 56842.629 | K30: =K8*Assumptions!$D$42 -> 61390.04 | L30: =L8*Assumptions!$D$42 -> 65994.293 | M30: =M8*Assumptions!$D$42 -> 70613.893
B31: FCF Margin % | C31: =C30/C8 -> 0.21722288 | D31: =D30/D8 -> 0.19287733 | E31: =E30/E8 -> 0.17254655 | F31: =F30/F8 -> 0.17305609 | G31: =G30/G8 -> 0.17622315 | H31: =H30/H8 -> 0.17980983 | I31: =I30/I8 -> 0.18 | J31: =J30/J8 -> 0.18 | ... M31: =M30/M8 -> 0.18
B33: Note: FY26 = year ended March 2026 (latest complete fiscal year per screener.in). Projections hold OPM, D&A%, and FCF margin constant at FY26 levels — a simplifying assumption; interest expense held flat in absolute terms.

Sheet DCF Valuation
B2: TCS — DCF Valuation (FCFF Approach)
B3: Discounts projected Free Cash Flow to Firm at WACC; Terminal Value via Gordon Growth Model
B5: (₹ Crores) | C5: FY27E | D5: FY28E | E5: FY29E | F5: FY30E | G5: FY31E
B7: Year Number (n) | C7: 1 | D7: 2 | E7: 3 | F7: 4 | G7: 5
B8: Projected FCF (from 3-Statement Model) | C8: ='3-Statement Model'!I30 -> 52389.52 | D8: ='3-Statement Model'!J30 -> 56842.629 | E8: ='3-Statement Model'!K30 -> 61390.04 | F8: ='3-Statement Model'!L30 -> 65994.293 | G8: ='3-Statement Model'!M30 -> 70613.893
B9: Discount Factor = 1 / (1+WACC)^n | C9: =1/(1+Assumptions!$D$24)^C7 -> 0.89457189 | D9: =1/(1+Assumptions!$D$24)^D7 -> 0.80025887 | E9: =1/(1+Assumptions!$D$24)^E7 -> 0.71588909 | F9: =1/(1+Assumptions!$D$24)^F7 -> 0.64041425 | G9: =1/(1+Assumptions!$D$24)^G7 -> 0.57289659
B10: PV of FCF | C10: =C8*C9 -> 46866.192 | D10: =D8*D9 -> 45488.818 | E10: =E8*E9 -> 43948.46 | F10: =F8*F9 -> 42263.686 | G10: =G8*G9 -> 40454.459
B12: TERMINAL VALUE
B13: FCF in Terminal Year + 1 = FY31E FCF × (1+g) | D13: =G8*(1+Assumptions!$D$27) -> 74144.588
B14: Terminal Value (at end of FY31) = FCF÷(WACC−g) | D14: =D13/(Assumptions!$D$24-Assumptions!$D$27) -> 1092721.5
B15: PV of Terminal Value = TV × Discount Factor (Yr 5) | D15: =D14*G9 -> 626016.41
B17: ENTERPRISE TO EQUITY VALUE BRIDGE
B18: Sum of PV of Explicit FCF (FY27E–FY31E) | D18: =SUM(C10:G10) -> 219021.61
B19: PV of Terminal Value | D19: =D15 -> 626016.41
B20: Enterprise Value | D20: =D18+D15 -> 845038.03
B21: Add: Net Cash / (Net Debt) | D21: =Assumptions!$D$32 -> 37431
B22: Equity Value | D22: =D20+D21 -> 882469.03
B23: ÷ Shares Outstanding (Cr) | D23: =Assumptions!$D$33 -> 361.89
B24: Intrinsic Value per Share (₹) | D24: =D22/Assumptions!$D$33 -> 2438.5007
B26: VALUATION VERDICT
B27: Current Market Price (₹) | D27: =Assumptions!$D$34 -> 2268
B28: Implied Upside / (Downside) | D28: =(D24-D27)/D27 -> 0.075176685
B29: Verdict | D29: =IF(D28>0.1,"UNDERVALUED",IF(D28<-0.1,"OVERVALUED","FAIRLY VALUED")) -> FAIRLY VALUED
B31: Standard DCF caveats apply: intrinsic value is highly sensitive to WACC and terminal growth assumptions (see Sensitivity Analysis sheet). This is a simplified single-scenario model built for demonstration purposes, not a substitute for a full analyst model with scenario/probability weighting.

Sheet Sensitivity Analysis
B2: TCS — Sensitivity Analysis
B3: Implied Intrinsic Value per Share (₹) — WACC (rows) × Terminal Growth Rate (columns)
B4: Each cell independently recomputes the DCF (5-yr FCF discounted + terminal value) at that WACC/growth combination.
B6: WACC ↓ / Terminal g → | C6: 0.03 | D6: 0.04 | E6: 0.05 | F6: 0.06 | G6: 0.07
B7: 0.0979 | C7: =(('3-Statement Model'!I30/(1+$B7)^1+'3-Statement Model'!J30/(1+$B7)^2+'3-Statement Model'!K30/(1+$B7)^3+'3-Statement Model'!L30/(1+$B7)^4+'3-Statement Model'!M30/(1+$B7)^5)+('3-Statement Model'!M30*(1+C$6)/($B7-C$6))/(1+$B7)^5+Assumptions!$D$32)/Assumptions!$D$33 -> 2597.1385 | D7: =(('3-Statement Model'!I30/(1+$B7)^1+'3-Statement Model'!J30/(1+$B7)^2+'3-Statement Model'!K30/(1+$B7)^3+'3-Statement Model'!L30/(1+$B7)^4+'3-Statement Model'!M30/(1+$B7)^5)+('3-Statement Model'!M30*(1+D$6)/($B7-D$6))/(1+$B7)^5+Assumptions!$D$32)/Assumptions!$D$33 -> 2938.7356 | E7: =(('3-Statement Model'!I30/(1+$B7)^1+'3-Statement Model'!J30/(1+$B7)^2+'3-Statement Model'!K30/(1+$B7)^3+'3-Statement Model'!L30/(1+$B7)^4+'3-Statement Model'!M30/(1+$B7)^5)+('3-Statement Model'!M30*(1+E$6)/($B7-E$6))/(1+$B7)^5+Assumptions!$D$32)/Assumptions!$D$33 -> 3422.9618 | F7: =(('3-Statement Model'!I30/(1+$B7)^1+'3-Statement Model'!J30/(1+$B7)^2+'3-Statement Model'!K30/(1+$B7)^3+'3-Statement Model'!L30/(1+$B7)^4+'3-Statement Model'!M30/(1+$B7)^5)+('3-Statement Model'!M30*(1+F$6)/($B7-F$6))/(1+$B7)^5+Assumptions!$D$32)/Assumptions!$D$33 -> 4162.7165 | G7: =(('3-Statement Model'!I30/(1+$B7)^1+'3-Statement Model'!J30/(1+$B7)^2+'3-Statement Model'!K30/(1+$B7)^3+'3-Statement Model'!L30/(1+$B7)^4+'3-Statement Model'!M30/(1+$B7)^5)+('3-Statement Model'!M30*(1+G$6)/($B7-G$6))/(1+$B7)^5+Assumptions!$D$32)/Assumptions!$D$33 -> 5432.7612
B8: 0.1079 | C8: =(('3-Statement Model'!I30/(1+$B8)^1+'3-Statement Model'!J30/(1+$B8)^2+'3-Statement Model'!K30/(1+$B8)^3+'3-Statement Model'!L30/(1+$B8)^4+'3-Statement Model'!M30/(1+$B8)^5)+('3-Statement Model'!M30*(1+C$6)/($B8-C$6))/(1+$B8)^5+Assumptions!$D$32)/Assumptions!$D$33 -> 2270.3963 | D8: =(('3-Statement Model'!I30/(1+$B8)^1+'3-Statement Model'!J30/(1+$B8)^2+'3-Statement Model'!K30/(1+$B8)^3+'3-Statement Model'!L30/(1+$B8)^4+'3-Statement Model'!M30/(1+$B8)^5)+('3-Statement Model'!M30*(1+D$6)/($B8-D$6))/(1+$B8)^5+Assumptions!$D$32)/Assumptions!$D$33 -> 2515.2485 | E8: =(('3-Statement Model'!I30/(1+$B8)^1+'3-Statement Model'!J30/(1+$B8)^2+'3-Statement Model'!K30/(1+$B8)^3+'3-Statement Model'!L30/(1+$B8)^4+'3-Statement Model'!M30/(1+$B8)^5)+('3-Statement Model'!M30*(1+E$6)/($B8-E$6))/(1+$B8)^5+Assumptions!$D$32)/Assumptions!$D$33 -> 2844.6784 | F8: =(('3-Statement Model'!I30/(1+$B8)^1+'3-Statement Model'!J30/(1+$B8)^2+'3-Statement Model'!K30/(1+$B8)^3+'3-Statement Model'!L30/(1+$B8)^4+'3-Statement Model'!M30/(1+$B8)^5)+('3-Statement Model'!M30*(1+F$6)/($B8-F$6))/(1+$B8)^5+Assumptions!$D$32)/Assumptions!$D$33 -> 3311.6573 | G8: =(('3-Statement Model'!I30/(1+$B8)^1+'3-Statement Model'!J30/(1+$B8)^2+'3-Statement Model'!K30/(1+$B8)^3+'3-Statement Model'!L30/(1+$B8)^4+'3-Statement Model'!M30/(1+$B8)^5)+('3-Statement Model'!M30*(1+G$6)/($B8-G$6))/(1+$B8)^5+Assumptions!$D$32)/Assumptions!$D$33 -> 4025.0631
B9: 0.1179 | C9: =(('3-Statement Model'!I30/(1+$B9)^1+'3-Statement Model'!J30/(1+$B9)^2+'3-Statement Model'!K30/(1+$B9)^3+'3-Statement Model'!L30/(1+$B9)^4+'3-Statement Model'!M30/(1+$B9)^5)+('3-Statement Model'!M30*(1+C$6)/($B9-C$6))/(1+$B9)^5+Assumptions!$D$32)/Assumptions!$D$33 -> 2018.1993 | D9: =(('3-Statement Model'!I30/(1+$B9)^1+'3-Statement Model'!J30/(1+$B9)^2+'3-Statement Model'!K30/(1+$B9)^3+'3-Statement Model'!L30/(1+$B9)^4+'3-Statement Model'!M30/(1+$B9)^5)+('3-Statement Model'!M30*(1+D$6)/($B9-D$6))/(1+$B9)^5+Assumptions!$D$32)/Assumptions!$D$33 -> 2200.6625 | E9: =(('3-Statement Model'!I30/(1+$B9)^1+'3-Statement Model'!J30/(1+$B9)^2+'3-Statement Model'!K30/(1+$B9)^3+'3-Statement Model'!L30/(1+$B9)^4+'3-Statement Model'!M30/(1+$B9)^5)+('3-Statement Model'!M30*(1+E$6)/($B9-E$6))/(1+$B9)^5+Assumptions!$D$32)/Assumptions!$D$33 -> 2436.8705 | F9: =(('3-Statement Model'!I30/(1+$B9)^1+'3-Statement Model'!J30/(1+$B9)^2+'3-Statement Model'!K30/(1+$B9)^3+'3-Statement Model'!L30/(1+$B9)^4+'3-Statement Model'!M30/(1+$B9)^5)+('3-Statement Model'!M30*(1+F$6)/($B9-F$6))/(1+$B9)^5+Assumptions!$D$32)/Assumptions!$D$33 -> 2754.6701 | G9: =(('3-Statement Model'!I30/(1+$B9)^1+'3-Statement Model'!J30/(1+$B9)^2+'3-Statement Model'!K30/(1+$B9)^3+'3-Statement Model'!L30/(1+$B9)^4+'3-Statement Model'!M30/(1+$B9)^5)+('3-Statement Model'!M30*(1+G$6)/($B9-G$6))/(1+$B9)^5+Assumptions!$D$32)/Assumptions!$D$33 -> 3205.1628
B10: 0.1279 | C10: =(('3-Statement Model'!I30/(1+$B10)^1+'3-Statement Model'!J30/(1+$B10)^2+'3-Statement Model'!K30/(1+$B10)^3+'3-Statement Model'!L30/(1+$B10)^4+'3-Statement Model'!M30/(1+$B10)^5)+('3-Statement Model'!M30*(1+C$6)/($B10-C$6))/(1+$B10)^5+Assumptions!$D$32)/Assumptions!$D$33 -> 1817.6961 | D10: =(('3-Statement Model'!I30/(1+$B10)^1+'3-Statement Model'!J30/(1+$B10)^2+'3-Statement Model'!K30/(1+$B10)^3+'3-Statement Model'!L30/(1+$B10)^4+'3-Statement Model'!M30/(1+$B10)^5)+('3-Statement Model'!M30*(1+D$6)/($B10-D$6))/(1+$B10)^5+Assumptions!$D$32)/Assumptions!$D$33 -> 1957.803 | E10: =(('3-Statement Model'!I30/(1+$B10)^1+'3-Statement Model'!J30/(1+$B10)^2+'3-Statement Model'!K30/(1+$B10)^3+'3-Statement Model'!L30/(1+$B10)^4+'3-Statement Model'!M30/(1+$B10)^5)+('3-Statement Model'!M30*(1+E$6)/($B10-E$6))/(1+$B10)^5+Assumptions!$D$32)/Assumptions!$D$33 -> 2133.8809 | F10: =(('3-Statement Model'!I30/(1+$B10)^1+'3-Statement Model'!J30/(1+$B10)^2+'3-Statement Model'!K30/(1+$B10)^3+'3-Statement Model'!L30/(1+$B10)^4+'3-Statement Model'!M30/(1+$B10)^5)+('3-Statement Model'!M30*(1+F$6)/($B10-F$6))/(1+$B10)^5+Assumptions!$D$32)/Assumptions!$D$33 -> 2361.8227 | G10: =(('3-Statement Model'!I30/(1+$B10)^1+'3-Statement Model'!J30/(1+$B10)^2+'3-Statement Model'!K30/(1+$B10)^3+'3-Statement Model'!L30/(1+$B10)^4+'3-Statement Model'!M30/(1+$B10)^5)+('3-Statement Model'!M30*(1+G$6)/($B10-G$6))/(1+$B10)^5+Assumptions!$D$32)/Assumptions!$D$33 -> 2668.5009
B11: 0.1379 | C11: =(('3-Statement Model'!I30/(1+$B11)^1+'3-Statement Model'!J30/(1+$B11)^2+'3-Statement Model'!K30/(1+$B11)^3+'3-Statement Model'!L30/(1+$B11)^4+'3-Statement Model'!M30/(1+$B11)^5)+('3-Statement Model'!M30*(1+C$6)/($B11-C$6))/(1+$B11)^5+Assumptions!$D$32)/Assumptions!$D$33 -> 1654.507 | D11: =(('3-Statement Model'!I30/(1+$B11)^1+'3-Statement Model'!J30/(1+$B11)^2+'3-Statement Model'!K30/(1+$B11)^3+'3-Statement Model'!L30/(1+$B11)^4+'3-Statement Model'!M30/(1+$B11)^5)+('3-Statement Model'!M30*(1+D$6)/($B11-D$6))/(1+$B11)^5+Assumptions!$D$32)/Assumptions!$D$33 -> 1764.6845 | E11: =(('3-Statement Model'!I30/(1+$B11)^1+'3-Statement Model'!J30/(1+$B11)^2+'3-Statement Model'!K30/(1+$B11)^3+'3-Statement Model'!L30/(1+$B11)^4+'3-Statement Model'!M30/(1+$B11)^5)+('3-Statement Model'!M30*(1+E$6)/($B11-E$6))/(1+$B11)^5+Assumptions!$D$32)/Assumptions!$D$33 -> 1899.9309 | F11: =(('3-Statement Model'!I30/(1+$B11)^1+'3-Statement Model'!J30/(1+$B11)^2+'3-Statement Model'!K30/(1+$B11)^3+'3-Statement Model'!L30/(1+$B11)^4+'3-Statement Model'!M30/(1+$B11)^5)+('3-Statement Model'!M30*(1+F$6)/($B11-F$6))/(1+$B11)^5+Assumptions!$D$32)/Assumptions!$D$33 -> 2069.9003 | G11: =(('3-Statement Model'!I30/(1+$B11)^1+'3-Statement Model'!J30/(1+$B11)^2+'3-Statement Model'!K30/(1+$B11)^3+'3-Statement Model'!L30/(1+$B11)^4+'3-Statement Model'!M30/(1+$B11)^5)+('3-Statement Model'!M30*(1+G$6)/($B11-G$6))/(1+$B11)^5+Assumptions!$D$32)/Assumptions!$D$33 -> 2289.9344
B12: 0.1479 | C12: =(('3-Statement Model'!I30/(1+$B12)^1+'3-Statement Model'!J30/(1+$B12)^2+'3-Statement Model'!K30/(1+$B12)^3+'3-Statement Model'!L30/(1+$B12)^4+'3-Statement Model'!M30/(1+$B12)^5)+('3-Statement Model'!M30*(1+C$6)/($B12-C$6))/(1+$B12)^5+Assumptions!$D$32)/Assumptions!$D$33 -> 1519.1313 | D12: =(('3-Statement Model'!I30/(1+$B12)^1+'3-Statement Model'!J30/(1+$B12)^2+'3-Statement Model'!K30/(1+$B12)^3+'3-Statement Model'!L30/(1+$B12)^4+'3-Statement Model'!M30/(1+$B12)^5)+('3-Statement Model'!M30*(1+D$6)/($B12-D$6))/(1+$B12)^5+Assumptions!$D$32)/Assumptions!$D$33 -> 1607.4722 | E12: =(('3-Statement Model'!I30/(1+$B12)^1+'3-Statement Model'!J30/(1+$B12)^2+'3-Statement Model'!K30/(1+$B12)^3+'3-Statement Model'!L30/(1+$B12)^4+'3-Statement Model'!M30/(1+$B12)^5)+('3-Statement Model'!M30*(1+E$6)/($B12-E$6))/(1+$B12)^5+Assumptions!$D$32)/Assumptions!$D$33 -> 1713.8604 | F12: =(('3-Statement Model'!I30/(1+$B12)^1+'3-Statement Model'!J30/(1+$B12)^2+'3-Statement Model'!K30/(1+$B12)^3+'3-Statement Model'!L30/(1+$B12)^4+'3-Statement Model'!M30/(1+$B12)^5)+('3-Statement Model'!M30*(1+F$6)/($B12-F$6))/(1+$B12)^5+Assumptions!$D$32)/Assumptions!$D$33 -> 1844.4551 | G12: =(('3-Statement Model'!I30/(1+$B12)^1+'3-Statement Model'!J30/(1+$B12)^2+'3-Statement Model'!K30/(1+$B12)^3+'3-Statement Model'!L30/(1+$B12)^4+'3-Statement Model'!M30/(1+$B12)^5)+('3-Statement Model'!M30*(1+G$6)/($B12-G$6))/(1+$B12)^5+Assumptions!$D$32)/Assumptions!$D$33 -> 2008.5787
B15: Highlighted cell ≈ base-case scenario (WACC ~11.8%, terminal growth 5.0%) used in the main DCF Valuation sheet.
B16: Reading the table: moving right (higher terminal growth) or down softer WACC both increase intrinsic value — this is the single biggest source of uncertainty in any DCF, which is why a range matters more than a point estimate.
